TRTLservices/__init__.py
TRTLservices/lib.py
ts_api_py-0.9.2.dist-info/LICENSE
ts_api_py-0.9.2.dist-info/METADATA
ts_api_py-0.9.2.dist-info/WHEEL
ts_api_py-0.9.2.dist-info/top_level.txt
ts_api_py-0.9.2.dist-info/RECORD
