Metadata-Version: 2.1
Name: ts-api-py
Version: 0.9.2
Summary: Python wrapper to interact with the TRTL Services API.
Home-page: https://github.com/trtl-services/ts-api-py
Author: fexra
Author-email: fexra@protonmail.com
License: UNKNOWN
Platform: UNKNOWN
Classifier: Programming Language :: Python :: 3
Classifier: License :: OSI Approved :: GNU Affero General Public License v3
